{
  "KAREN_STRIKE.title": "Strike",
  "KAREN_STRIKE.description": "Deal {Damage:diff()} damage.",
  "KAREN_DEFEND.title": "Defend",
  "KAREN_DEFEND.description": "Gain {Block:diff()} [gold]Block[/gold].",

  "KAREN_SHINE_KEYWORD.title": "Shine",
  "KAREN_SHINE_KEYWORD.description": "Each time this card is played, its [gold]Shine[/gold] decreases by 1. When it reaches 0, the card is permanently removed from your deck.",

  "KAREN_SHINE_STRIKE.title": "Shine Strike",
  "KAREN_SHINE_STRIKE.description": "Deal {Damage:diff()} damage.",

  "KAREN_SHINE_DEFEND.title": "Shine Defend",
  "KAREN_SHINE_DEFEND.description": "Gain {Block:diff()} [gold]Block[/gold].",

  "KAREN_PROMISE_DEFEND.title": "Promise Defense",
  "KAREN_PROMISE_DEFEND.description": "Gain {Block:diff()} [gold]Block[/gold]. Put {Cards:diff()} card(s) from your hand into the [gold]Promise Pile[/gold].",

  "KAREN_PROMISE_DRAW.title": "Fulfill Promise",
  "KAREN_PROMISE_DRAW.description": "Deal {Damage:diff()} damage. Take {Cards:diff()} card(s) from the [gold]Promise Pile[/gold] into your hand.",

  "KAREN_PLACEHOLDER_POWER.title": "Placeholder Power",
  "KAREN_PLACEHOLDER_POWER.description": "[gray]A placeholder power card. No effect yet.[/gray]",

  "KAREN_PLACEHOLDER_UNCOMMON_SKILL.title": "Placeholder Uncommon Skill",
  "KAREN_PLACEHOLDER_UNCOMMON_SKILL.description": "[gray]A placeholder uncommon skill card. No effect yet.[/gray]",

  "KAREN_PLACEHOLDER_RARE_SKILL.title": "Placeholder Rare Skill",
  "KAREN_PLACEHOLDER_RARE_SKILL.description": "[gray]A placeholder rare skill card. No effect yet.[/gray]"
}
